{
  "toolPathName":["d716912c-ed26-486a-8ed3-a25c55dd32da.json"],
  "toolPathBaseName":["C:\\Users\\abogomolov.RC\\Documents\\github\\fusion_scripts\\ToolXChangeFiles\\"],
  "toolDate":["09-06-2019|17:11:43"],
  "users":["abogomolov"],
  "usersToolName":["mirrors01"],
  "toolRaw":["{\n\tTools = ordered() {\n\t\tBitmap4 = BitmapMask {\n\t\t\tViewInfo = OperatorInfo { Pos = { 4351.27001953125, -201.391006469727 } },\n\t\t\tInputs = {\n\t\t\t\tClippingMode = Input { Value = FuID { \"None\" } },\n\t\t\t\tClipWhite = Input { Value = 0 },\n\t\t\t\tHigh = Input { Value = 0.696 },\n\t\t\t\tLow = Input { Value = 0.031 },\n\t\t\t\tImage = Input {\n\t\t\t\t\tSource = \"Mask\",\n\t\t\t\t\tSourceOp = \"Bitmap2\"\n\t\t\t\t},\n\t\t\t\tChannel = Input { Value = FuID { \"Luminance\" } },\n\t\t\t\tMaskHeight = Input { Value = 1080 },\n\t\t\t\tMaskWidth = Input { Value = 1920 },\n\t\t\t\tClipBlack = Input { Value = 0 },\n\t\t\t\tProcessMode = Input { Value = FuID { \"PAL\" } },\n\t\t\t\tPixelAspect = Input { Value = { 1, 1 } }\n\t\t\t}\n\t\t},\n\t\tTransform2 = Transform {\n\t\t\tViewInfo = OperatorInfo { Pos = { 4351.27001953125, -350.678985595703 } },\n\t\t\tInputs = {\n\t\t\t\tInput = Input {\n\t\t\t\t\tSource = \"Output\",\n\t\t\t\t\tSourceOp = \"Loader2\"\n\t\t\t\t},\n\t\t\t\tAngle = Input {\n\t\t\t\t\tExpression = \"-time/4\",\n\t\t\t\t\tValue = -72.25\n\t\t\t\t}\n\t\t\t}\n\t\t},\n\t\tbreakpoint1 = Underlay {\n\t\t\tViewInfo = UnderlayInfo {\n\t\t\t\tPos = { 4350.2001953125, -438.733001708984 },\n\t\t\t\tSize = { 174.136001586914, 83.8835983276367 }\n\t\t\t}\n\t\t},\n\t\tDisplace1 = Displace {\n\t\t\tCtrlWZoom = false,\n\t\t\tViewInfo = OperatorInfo { Pos = { 4351.27001953125, -16.3609008789063 } },\n\t\t\tInputs = {\n\t\t\t\tCenter = Input { Value = { 0.596804054824883, 0.365023269342641 } },\n\t\t\t\tRefractionStrength = Input { Value = 0.53 },\n\t\t\t\tChannel = Input { Value = 3 },\n\t\t\t\tLightAngle = Input { Value = 326.2 },\n\t\t\t\tSpread = Input { Value = 0.332 },\n\t\t\t\tForeground = Input {\n\t\t\t\t\tSource = \"Mask\",\n\t\t\t\t\tSourceOp = \"Bitmap4\"\n\t\t\t\t},\n\t\t\t\tOffset = Input { Value = 0.0342 },\n\t\t\t\tLightPower = Input { Value = 0.115 },\n\t\t\t\tLightChannel = Input { Value = 4 }\n\t\t\t}\n\t\t},\n\t\tSaver2_1 = Saver {\n\t\t\tPassThrough = true,\n\t\t\tUserControls = ordered() {\n\t\t\t\tML = {\n\t\t\t\t\tLINKID_DataType = \"Number\",\n\t\t\t\t\tINP_Default = 0,\n\t\t\t\t\tLINKS_Name = \"Make Loader\",\n\t\t\t\t\tINPID_InputControl = \"ButtonControl\",\n\t\t\t\t\tBTNCS_Execute = \" tool = comp.ActiveTool; comp:RunScript(\\\"Scripts:Comp/Saver Tools/LoaderFromSaver.lua\\\", tool) \",\n\t\t\t\t\tICS_ControlPage = \"File\"\n\t\t\t\t}\n\t\t\t},\n\t\t\tInputs = {\n\t\t\t\tClip = Input {\n\t\t\t\t\tValue = Clip {\n\t\t\t\t\t\tFilename = \"RENDER:Summer_LUG\\\\fractal_render_.exr\",\n\t\t\t\t\t\tTrimIn = 0,\n\t\t\t\t\t\tLength = 0,\n\t\t\t\t\t\tGlobalEnd = 0,\n\t\t\t\t\t\tExtendLast = 0,\n\t\t\t\t\t\tSaving = true,\n\t\t\t\t\t\tDepth = 0,\n\t\t\t\t\t\tTimeCode = 0,\n\t\t\t\t\t\tGlobalStart = -2000000000,\n\t\t\t\t\t\tFormatID = \"OpenEXRFormat\",\n\t\t\t\t\t\tAspectMode = 0,\n\t\t\t\t\t\tLoop = 1,\n\t\t\t\t\t\tExtendFirst = 0\n\t\t\t\t\t}\n\t\t\t\t},\n\t\t\t\t[\"Gamut.SLogVersion\"] = Input { Value = FuID { \"SLog2\" } },\n\t\t\t\tOutputFormat = Input { Value = FuID { \"OpenEXRFormat\" } },\n\t\t\t\tProcessWhenBlendIs00 = Input { Value = 0 },\n\t\t\t\tInput = Input {\n\t\t\t\t\tSource = \"Output\",\n\t\t\t\t\tSourceOp = \"FractalNoise1\"\n\t\t\t\t}\n\t\t\t},\n\t\t\tViewInfo = OperatorInfo { Pos = { 4349.1298828125, -438.733001708984 } }\n\t\t},\n\t\tBitmap2 = BitmapMask {\n\t\t\tViewInfo = OperatorInfo { Pos = { 4351.27001953125, -313.989013671875 } },\n\t\t\tInputs = {\n\t\t\t\tClippingMode = Input { Value = FuID { \"None\" } },\n\t\t\t\tImage = Input {\n\t\t\t\t\tSource = \"Output\",\n\t\t\t\t\tSourceOp = \"Transform2\"\n\t\t\t\t},\n\t\t\t\tSoftEdge = Input { Value = 0.002 },\n\t\t\t\tMaskHeight = Input { Value = 2000 },\n\t\t\t\tChannel = Input { Value = FuID { \"Luminance\" } },\n\t\t\t\tMaskWidth = Input { Value = 2000 },\n\t\t\t\tDepth = Input { Value = 3 },\n\t\t\t\tOutputSize = Input { Value = FuID { \"Custom\" } },\n\t\t\t\tPixelAspect = Input { Value = { 1, 1 } }\n\t\t\t}\n\t\t},\n\t\tCalculation1 = Calculation {\n\t\t\tCtrlWZoom = false,\n\t\t\tCtrlWShown = false,\n\t\t\tInputs = {\n\t\t\t\tOperator = Input { Value = 3 },\n\t\t\t\tSecondOperand = Input {\n\t\t\t\t\tSource = \"Value\",\n\t\t\t\t\tSourceOp = \"Publish1_1\"\n\t\t\t\t},\n\t\t\t\tFirstOperand = Input { Value = 1 }\n\t\t\t}\n\t\t},\n\t\tPublish1_1 = PublishNumber {\n\t\t\tCtrlWZoom = false,\n\t\t\tCtrlWShown = false,\n\t\t\tInputs = {\n\t\t\t\tValue = Input { Value = 0.5 }\n\t\t\t}\n\t\t},\n\t\tLoader2 = Loader {\n\t\t\tViewInfo = OperatorInfo { Pos = { 4351.27001953125, -398.848999023438 } },\n\t\t\tClips = {\n\t\t\t\tClip {\n\t\t\t\t\tTimeCode = 0,\n\t\t\t\t\tFilename = \"RENDER:Summer_LUG\\\\fractal_render_0000.exr\",\n\t\t\t\t\tTrimIn = 0,\n\t\t\t\t\tGlobalStart = 0,\n\t\t\t\t\tLength = 290,\n\t\t\t\t\tGlobalEnd = 289,\n\t\t\t\t\tExtendFirst = 0,\n\t\t\t\t\tAspectMode = 0,\n\t\t\t\t\tDepth = 0,\n\t\t\t\t\tTrimOut = 289,\n\t\t\t\t\tID = \"Clip1\",\n\t\t\t\t\tFormatID = \"OpenEXRFormat\",\n\t\t\t\t\tLoop = 1,\n\t\t\t\t\tLengthSetManually = true,\n\t\t\t\t\tExtendLast = 0\n\t\t\t\t}\n\t\t\t},\n\t\t\tInputs = {\n\t\t\t\t[\"Clip1.OpenEXRFormat.RedName\"] = Input { Value = FuID { \"R\" } },\n\t\t\t\t[\"Gamut.SLogVersion\"] = Input { Value = FuID { \"SLog2\" } },\n\t\t\t\t[\"Clip1.OpenEXRFormat.BlueName\"] = Input { Value = FuID { \"B\" } },\n\t\t\t\t[\"Clip1.OpenEXRFormat.AlphaName\"] = Input { Value = FuID { \"A\" } },\n\t\t\t\t[\"Clip1.OpenEXRFormat.GreenName\"] = Input { Value = FuID { \"G\" } }\n\t\t\t}\n\t\t},\n\t\tFractalNoise1 = Fuse.FractalNoise {\n\t\t\tVersion = 110,\n\t\t\tViewInfo = OperatorInfo { Pos = { 4349.1298828125, -477.563995361328 } },\n\t\t\tInputs = {\n\t\t\t\tGamma = Input { Value = 0.481 },\n\t\t\t\t[\"Gamut.SLogVersion\"] = Input { Value = FuID { \"SLog2\" } },\n\t\t\t\tSpeed = Input { Value = 0.056 },\n\t\t\t\tOffset = Input { Value = 1 },\n\t\t\t\tBColor = Input { Value = 1 },\n\t\t\t\tGain = Input { Value = 0.679 },\n\t\t\t\tw_detail = Input { Value = 0.0035 },\n\t\t\t\tScale = Input { Value = 0.981 },\n\t\t\t\tDepth = Input { Value = 3 },\n\t\t\t\tProcessMode = Input { Value = FuID { \"FullFrames\" } },\n\t\t\t\tContrast = Input { Value = 1.075 },\n\t\t\t\tTransform = Input { Value = 1 },\n\t\t\t\t[\"Fractal Type\"] = Input { Value = 5 },\n\t\t\t\tHeight = Input { Value = 2000 },\n\t\t\t\tWidth = Input { Value = 2000 }\n\t\t\t}\n\t\t},\n\t\tSaver_2sBlend = BezierSpline {\n\t\t\tSplineColor = { Red = 205, Green = 205, Blue = 205 },\n\t\t\tNameSet = true,\n\t\t\tKeyFrames = {\n\t\t\t\t[48] = { 1, RH = { 48.3333333333333, 0.666666666666667 }, Flags = { Linear = true } },\n\t\t\t\t[49] = { 0, Flags = { Linear = true }, LH = { 48.6666666666667, 0.333333333333333 } }\n\t\t\t}\n\t\t}\n\t}\n}"],
  "usersToolComment":[""]
}